ALU_FSM/FSM/ALU_ROL_5bit.v
module ALU_ROL_5bit 
(
    input [4:0] A,
    input [2:0] B,  
    output reg [4:0] R
);


    always @(*) begin
        case(B)
            3'b000: R = A;                     
            3'b001: R = {A[3:0], A[4]};       
            3'b010: R = {A[2:0], A[4:3]};      
            3'b011: R = {A[1:0], A[4:2]};       
            3'b100: R = {A[0], A[4:1]};
            3'b101: R = A;
            3'b110: R = {A[3:1], A[4]}; // repeat rotations if the value is greater than 5
            3'b111: R = {A[2:0], A[4:3]}; // repeat rotations if the value is greater than 5
            default: R = A;                   
        endcase
    end
    
endmodule

ALU_FSM/ALU/ALU_AND_5bit.v
module ALU_AND_5bit 
(
    input wire [4:0] A,B,  
    output wire [4:0] R    
);
    assign R = (A & B);

endmodule

ALU_FSM/FSM/ALU.v
module ALU
(
    input wire [4:0] A, B,                   
    input wire OP,    
    output reg [4:0] R,     
    output wire CF,
    output wire SF,
    output wire ZF           
);

    // reg Sel;
    wire [4:0] R_AND, R_ROL;
    // wire CF_ADD_SUB;

    // Instantiate modules

    ALU_AND_5bit and1 (.A(A), .B(B), .R(R_AND));
    ALU_ROL_5bit rol1 (.A(A), .B(B[2:0]), .R(R_ROL));


    always @(*) 
    begin
        case (OP)
            1'b0: // AND
                begin 
                    R = R_AND;
                end
            1'b1: // ROL
                begin 
                    R = R_ROL;
                end
            default: 
                begin
                    R = 5'b00000;  
                end
        endcase
    end

    assign CF = 1'b0;
    assign SF = R[4];
    assign ZF = ~(R[4] | R[3] | R[2]| R[1]| R[0]);

endmodule

ALU_FSM/FSM/controller.v
module controller(
    input wire clk, reset,
    output reg [4:0] A, B,
    output reg OP
);


reg [2:0] pstate, nstate;

parameter [2:0] START       = 3'b000,
                ONE         = 3'b001,
                TWO         = 3'b010,
                THREE       = 3'b011,
                FINISH      = 3'b100;


always @(posedge clk or posedge reset)
begin
    if(reset)
        pstate <= START;
    else
        pstate <= nstate; 
end

always @(*)
begin

    A = 5'b00000;
    B = 5'b00000;
    OP = 1'b0;
    nstate = pstate;

    case (pstate)
        START:
        begin
            nstate = ONE;
        end
        ONE:
        begin
            A = 5'b11100;
            B = 5'b00011;
            OP = 1'b0;
            nstate = TWO;
        end
        TWO:
        begin
            
            A = 5'b10100;
            B = 5'b00010;
            OP = 1'b1;
            nstate = THREE;
        end
        THREE:
        begin
            
            A = 5'b11100;
            B = 5'b00100;
            OP = 1'b1;
            nstate = FINISH;
        end
        FINISH:
        begin
            nstate = START;
        end

        default: nstate = START;
    endcase
            
end

endmodule

ALU_FSM/FSM/top.v
module top
(
    input wire clk, reset,
    output wire [4:0] R,
    output wire flag
);

wire [4:0] A,B;
wire OP;
wire [4:0] R_result;
wire R_ZF;

controller controller1 (
    .clk(clk),
    .reset(reset),
    .A(A),
    .B(B),
    .OP(OP)
);

ALU datapath1 (
    .A(A),
    .B(B),
    .OP(OP),
    .R(R_result),
    .ZF(R_ZF)
);

assign R = R_result;
assign flag = ~R_ZF;

endmodule

ALU_FSM/FSM/top_tb.v
module top_tb;


reg clk, reset;
wire [4:0] R;
wire flag;

top uut(
    .clk(clk),
    .reset(reset),
    .R(R),
    .flag(flag)
);

initial begin
    clk = 0;
    forever #5 clk = ~clk;
end

initial begin
    $dumpfile("top_tb_test.vcd");
    $dumpvars(0, top_tb);

    reset = 1;
    #30;

    reset = 0;
    #30;

    reset = 1;
    #30;

    reset = 0;
    #100;
    $finish;
end

endmodule

ALU_FSM/FSM/top_tb_test.vcd
$date
	Tue Jun 10 23:49:57 2025
$end
$version
	Icarus Verilog
$end
$timescale
	1s
$end
$scope module top_tb $end
$var wire 1 ! flag $end
$var wire 5 " R [4:0] $end
$var reg 1 # clk $end
$var reg 1 $ reset $end
$scope module uut $end
$var wire 5 % R [4:0] $end
$var wire 1 # clk $end
$var wire 1 ! flag $end
$var wire 1 $ reset $end
$var wire 5 & R_result [4:0] $end
$var wire 1 ' R_ZF $end
$var wire 1 ( OP $end
$var wire 5 ) B [4:0] $end
$var wire 5 * A [4:0] $end
$scope module controller1 $end
$var wire 1 # clk $end
$var wire 1 $ reset $end
$var parameter 3 + FINISH $end
$var parameter 3 , ONE $end
$var parameter 3 - START $end
$var parameter 3 . THREE $end
$var parameter 3 / TWO $end
$var reg 5 0 A [4:0] $end
$var reg 5 1 B [4:0] $end
$var reg 1 ( OP $end
$var reg 3 2 nstate [2:0] $end
$var reg 3 3 pstate [2:0] $end
$upscope $end
$scope module datapath1 $end
$var wire 5 4 A [4:0] $end
$var wire 5 5 B [4:0] $end
$var wire 1 6 CF $end
$var wire 1 ( OP $end
$var wire 1 ' ZF $end
$var wire 1 7 SF $end
$var wire 5 8 R_ROL [4:0] $end
$var wire 5 9 R_AND [4:0] $end
$var reg 5 : R [4:0] $end
$scope module and1 $end
$var wire 5 ; A [4:0] $end
$var wire 5 < B [4:0] $end
$var wire 5 = R [4:0] $end
$upscope $end
$scope module rol1 $end
$var wire 5 > A [4:0] $end
$var wire 3 ? B [2:0] $end
$var reg 5 @ R [4:0] $end
$upscope $end
$upscope $end
$upscope $end
$upscope $end
$enddefinitions $end
$comment Show the parameter values. $end
$dumpall
b10 /
b11 .
b0 -
b1 ,
b100 +
$end
#0
$dumpvars
b0 @
b0 ?
b0 >
b0 =
b0 <
b0 ;
b0 :
b0 9
b0 8
07
06
b0 5
b0 4
b0 3
b1 2
b0 1
b0 0
b0 *
b0 )
0(
1'
b0 &
b0 %
1$
0#
b0 "
0!
$end
#5
1#
#10
0#
#15
1#
#20
0#
#25
1#
#30
0#
0$
#35
b11 ?
b111 8
b111 @
b10 2
b11 )
b11 1
b11 5
b11 <
b11100 *
b11100 0
b11100 4
b11100 ;
b11100 >
b1 3
1#
#40
0#
#45
1!
0'
17
b10010 "
b10010 %
b10010 &
b10010 :
b10 ?
b10010 8
b10010 @
b11 2
1(
b10 )
b10 1
b10 5
b10 <
b10100 *
b10100 0
b10100 4
b10100 ;
b10100 >
b10 3
1#
#50
0#
#55
07
b1110 "
b1110 %
b1110 &
b1110 :
b100 ?
b100 9
b100 =
b1110 8
b1110 @
b100 2
1(
b100 )
b100 1
b100 5
b100 <
b11100 *
b11100 0
b11100 4
b11100 ;
b11100 >
b11 3
1#
#60
0!
1'
b0 "
b0 %
b0 &
b0 :
b0 ?
b0 9
b0 =
b0 8
b0 @
b1 2
0(
b0 )
b0 1
b0 5
b0 <
b0 *
b0 0
b0 4
b0 ;
b0 >
b0 3
0#
1$
#65
1#
#70
0#
#75
1#
#80
0#
#85
1#
#90
0#
0$
#95
b11 ?
b111 8
b111 @
b10 2
b11 )
b11 1
b11 5
b11 <
b11100 *
b11100 0
b11100 4
b11100 ;
b11100 >
b1 3
1#
#100
0#
#105
1!
0'
17
b10010 "
b10010 %
b10010 &
b10010 :
b10 ?
b10010 8
b10010 @
b11 2
1(
b10 )
b10 1
b10 5
b10 <
b10100 *
b10100 0
b10100 4
b10100 ;
b10100 >
b10 3
1#
#110
0#
#115
07
b1110 "
b1110 %
b1110 &
b1110 :
b100 ?
b100 9
b100 =
b1110 8
b1110 @
b100 2
1(
b100 )
b100 1
b100 5
b100 <
b11100 *
b11100 0
b11100 4
b11100 ;
b11100 >
b11 3
1#
#120
0#
#125
0!
1'
b0 "
b0 %
b0 &
b0 :
b0 ?
b0 9
b0 =
b0 8
b0 @
b0 2
0(
b0 )
b0 1
b0 5
b0 <
b0 *
b0 0
b0 4
b0 ;
b0 >
b100 3
1#
#130
0#
#135
b1 2
b0 3
1#
#140
0#
#145
b11 ?
b111 8
b111 @
b10 2
b11 )
b11 1
b11 5
b11 <
b11100 *
b11100 0
b11100 4
b11100 ;
b11100 >
b1 3
1#
#150
0#
#155
1!
0'
17
b10010 "
b10010 %
b10010 &
b10010 :
b10 ?
b10010 8
b10010 @
b11 2
1(
b10 )
b10 1
b10 5
b10 <
b10100 *
b10100 0
b10100 4
b10100 ;
b10100 >
b10 3
1#
#160
0#
#165
07
b1110 "
b1110 %
b1110 &
b1110 :
b100 ?
b100 9
b100 =
b1110 8
b1110 @
b100 2
1(
b100 )
b100 1
b100 5
b100 <
b11100 *
b11100 0
b11100 4
b11100 ;
b11100 >
b11 3
1#
#170
0#
#175
0!
1'
b0 "
b0 %
b0 &
b0 :
b0 ?
b0 9
b0 =
b0 8
b0 @
b0 2
0(
b0 )
b0 1
b0 5
b0 <
b0 *
b0 0
b0 4
b0 ;
b0 >
b100 3
1#
#180
0#
#185
b1 2
b0 3
1#
